Workbook

Sheet Assumptions
A1: FY2026 Budget Assumptions
A3: Yellow cells = your inputs. All other tabs pull from this sheet.
A5: A. REVENUE ASSUMPTIONS
A6: Revenue Line | B6: FY2025 Actual ($) | C6: YoY Growth % | D6: FY2026 Budget ($) | E6: Q1 Weight | F6: Q2 Weight | G6: Notes
A7: Product A | D7: =B7*(1+C7) -> 0 | H7: Source: FY2025 Actuals, Internal
A8: Product B | D8: =B8*(1+C8) -> 0 | H8: Source: FY2025 Actuals, Internal
A9: Product C | D9: =B9*(1+C9) -> 0 | H9: Source: FY2025 Actuals, Internal
A10: Product D | D10: =B10*(1+C10) -> 0 | H10: Source: FY2025 Actuals, Internal
A11: Other Revenue | D11: =B11*(1+C11) -> 0 | H11: Source: FY2025 Actuals, Internal
A12: TOTAL REVENUE | B12: =SUM(B7:B11) -> 0 | C12: =SUM(C7:C11) -> 0 | D12: =SUM(D7:D11) -> 0
A14: B. MARGIN & COST ASSUMPTIONS
A15: Assumption | B15: Value | C15: Prior Year | D15: Change | E15: Unit | G15: Notes
A16: Gross Margin % | C16: 0.6 | D16: =B16-C16 -> -0.6 | E16: % of Revenue
A17: R&D % of Revenue | C17: 0.09 | D17: =B17-C17 -> -0.09 | E17: % of Revenue
A18: Sales & Marketing % | C18: 0.16 | D18: =B18-C18 -> -0.16 | E18: % of Revenue
A19: G&A % of Revenue | C19: 0.08 | D19: =B19-C19 -> -0.08 | E19: % of Revenue
A20: Depreciation () | C20: 165000 | D20: =B20-C20 -> -165000 | E20: $ Annual
A21: Interest Expense () | C21: 50000 | D21: =B21-C21 -> -50000 | E21: $ Annual
A22: Tax Rate % | C22: 0.21 | D22: =B22-C22 -> -0.21 | E22: % of EBT
A25: C. HEADCOUNT ASSUMPTIONS
A26: Department | B26: FY2025 HC | C26: FY2026 HC (Budget) | D26: Avg Salary ($)
A27: Engineering | B27: 45
A28: Sales | B28: 30
A29: Marketing | B29: 15
A30: G&A | B30: 20
A31: Operations | B31: 25
A32: TOTAL HEADCOUNT | B32: =SUM(B27:B31) -> 135 | C32: =SUM(C27:C31) -> 0

Sheet Budget_PL
A1: FY2026 Annual Budget — Monthly P&L
A3: P&L Line Item | B3: Jan | C3: Feb | D3: Mar | E3: Apr | F3: May | G3: Jun | H3: Jul | I3: Aug | J3: Sep | K3: Oct | L3: Nov | M3: Dec | N3: FY2026 Total | O3: FY2025 Actual | P3: YoY Var %
A5: REVENUE
A6: Product A | B6: =Assumptions!D7/12 -> 0 | C6: =Assumptions!D7/12 -> 0 | D6: =Assumptions!D7/12 -> 0 | E6: =Assumptions!D7/12 -> 0 | F6: =Assumptions!D7/12 -> 0 | G6: =Assumptions!D7/12 -> 0 | H6: =Assumptions!D7/12 -> 0 | I6: =Assumptions!D7/12 -> 0 | J6: =Assumptions!D7/12 -> 0 | K6: =Assumptions!D7/12 -> 0 | L6: =Assumptions!D7/12 -> 0 | M6: =Assumptions!D7/12 -> 0 | N6: =SUM(B6:M6) -> 0 | O6: =Assumptions!B7 -> 0 | P6: =IF(O6<>0,(N6-O6)/ABS(O6),0) -> 0
A7: Product B | B7: =Assumptions!D8/12 -> 0 | C7: =Assumptions!D8/12 -> 0 | D7: =Assumptions!D8/12 -> 0 | E7: =Assumptions!D8/12 -> 0 | F7: =Assumptions!D8/12 -> 0 | G7: =Assumptions!D8/12 -> 0 | H7: =Assumptions!D8/12 -> 0 | I7: =Assumptions!D8/12 -> 0 | J7: =Assumptions!D8/12 -> 0 | K7: =Assumptions!D8/12 -> 0 | L7: =Assumptions!D8/12 -> 0 | M7: =Assumptions!D8/12 -> 0 | N7: =SUM(B7:M7) -> 0 | O7: =Assumptions!B8 -> 0 | P7: =IF(O7<>0,(N7-O7)/ABS(O7),0) -> 0
A8: Product C | B8: =Assumptions!D9/12 -> 0 | C8: =Assumptions!D9/12 -> 0 | D8: =Assumptions!D9/12 -> 0 | E8: =Assumptions!D9/12 -> 0 | F8: =Assumptions!D9/12 -> 0 | G8: =Assumptions!D9/12 -> 0 | H8: =Assumptions!D9/12 -> 0 | I8: =Assumptions!D9/12 -> 0 | J8: =Assumptions!D9/12 -> 0 | K8: =Assumptions!D9/12 -> 0 | L8: =Assumptions!D9/12 -> 0 | M8: =Assumptions!D9/12 -> 0 | N8: =SUM(B8:M8) -> 0 | O8: =Assumptions!B9 -> 0 | P8: =IF(O8<>0,(N8-O8)/ABS(O8),0) -> 0
A9: Product D | B9: =Assumptions!D10/12 -> 0 | C9: =Assumptions!D10/12 -> 0 | D9: =Assumptions!D10/12 -> 0 | E9: =Assumptions!D10/12 -> 0 | F9: =Assumptions!D10/12 -> 0 | G9: =Assumptions!D10/12 -> 0 | H9: =Assumptions!D10/12 -> 0 | I9: =Assumptions!D10/12 -> 0 | J9: =Assumptions!D10/12 -> 0 | K9: =Assumptions!D10/12 -> 0 | L9: =Assumptions!D10/12 -> 0 | M9: =Assumptions!D10/12 -> 0 | N9: =SUM(B9:M9) -> 0 | O9: =Assumptions!B10 -> 0 | P9: =IF(O9<>0,(N9-O9)/ABS(O9),0) -> 0
A10: Other Revenue | B10: =Assumptions!D11/12 -> 0 | C10: =Assumptions!D11/12 -> 0 | D10: =Assumptions!D11/12 -> 0 | E10: =Assumptions!D11/12 -> 0 | F10: =Assumptions!D11/12 -> 0 | G10: =Assumptions!D11/12 -> 0 | H10: =Assumptions!D11/12 -> 0 | I10: =Assumptions!D11/12 -> 0 | J10: =Assumptions!D11/12 -> 0 | K10: =Assumptions!D11/12 -> 0 | L10: =Assumptions!D11/12 -> 0 | M10: =Assumptions!D11/12 -> 0 | N10: =SUM(B10:M10) -> 0 | O10: =Assumptions!B11 -> 0 | P10: =IF(O10<>0,(N10-O10)/ABS(O10),0) -> 0
A11: TOTAL REVENUE | B11: =SUM(B6:B10) -> 0 | C11: =SUM(C6:C10) -> 0 | D11: =SUM(D6:D10) -> 0 | E11: =SUM(E6:E10) -> 0 | F11: =SUM(F6:F10) -> 0 | G11: =SUM(G6:G10) -> 0 | H11: =SUM(H6:H10) -> 0 | I11: =SUM(I6:I10) -> 0 | ... O11: =SUM(O6:O10) -> 0 | P11: =IF(O11<>0,(N11-O11)/ABS(O11),0) -> 0
A13: COST OF GOODS SOLD
A14: Cost of Revenue | B14: =B11*(1-Assumptions!B16) -> 0 | C14: =C11*(1-Assumptions!B16) -> 0 | D14: =D11*(1-Assumptions!B16) -> 0 | E14: =E11*(1-Assumptions!B16) -> 0 | F14: =F11*(1-Assumptions!B16) -> 0 | G14: =G11*(1-Assumptions!B16) -> 0 | H14: =H11*(1-Assumptions!B16) -> 0 | I14: =I11*(1-Assumptions!B16) -> 0 | J14: =J11*(1-Assumptions!B16) -> 0 | K14: =K11*(1-Assumptions!B16) -> 0 | L14: =L11*(1-Assumptions!B16) -> 0 | M14: =M11*(1-Assumptions!B16) -> 0 | N14: =SUM(B14:M14) -> 0 | O14: =O11*(1-Assumptions!C16) -> 0 | P14: =IF(O14<>0,(N14-O14)/ABS(O14),0) -> 0
A15: GROSS PROFIT | B15: =B11-B14 -> 0 | C15: =C11-C14 -> 0 | D15: =D11-D14 -> 0 | E15: =E11-E14 -> 0 | F15: =F11-F14 -> 0 | G15: =G11-G14 -> 0 | H15: =H11-H14 -> 0 | I15: =I11-I14 -> 0 | ... O15: =O11-O14 -> 0 | P15: =IF(O15<>0,(N15-O15)/ABS(O15),0) -> 0
A16: Gross Margin % | B16: =IF(B11<>0,B15/B11,0) -> 0 | C16: =IF(C11<>0,C15/C11,0) -> 0 | D16: =IF(D11<>0,D15/D11,0) -> 0 | E16: =IF(E11<>0,E15/E11,0) -> 0 | F16: =IF(F11<>0,F15/F11,0) -> 0 | G16: =IF(G11<>0,G15/G11,0) -> 0 | H16: =IF(H11<>0,H15/H11,0) -> 0 | I16: =IF(I11<>0,I15/I11,0) -> 0 | ... O16: =IF(O11<>0,O15/O11,0) -> 0
A18: OPERATING EXPENSES
A19: Research & Development | B19: =B11*Assumptions!B17 -> 0 | C19: =C11*Assumptions!B17 -> 0 | D19: =D11*Assumptions!B17 -> 0 | E19: =E11*Assumptions!B17 -> 0 | F19: =F11*Assumptions!B17 -> 0 | G19: =G11*Assumptions!B17 -> 0 | H19: =H11*Assumptions!B17 -> 0 | I19: =I11*Assumptions!B17 -> 0 | J19: =J11*Assumptions!B17 -> 0 | K19: =K11*Assumptions!B17 -> 0 | L19: =L11*Assumptions!B17 -> 0 | M19: =M11*Assumptions!B17 -> 0 | N19: =SUM(B19:M19) -> 0 | O19: =O11*Assumptions!C17 -> 0 | P19: =IF(O19<>0,(N19-O19)/ABS(O19),0) -> 0
A20: Sales & Marketing | B20: =B11*Assumptions!B18 -> 0 | C20: =C11*Assumptions!B18 -> 0 | D20: =D11*Assumptions!B18 -> 0 | E20: =E11*Assumptions!B18 -> 0 | F20: =F11*Assumptions!B18 -> 0 | G20: =G11*Assumptions!B18 -> 0 | H20: =H11*Assumptions!B18 -> 0 | I20: =I11*Assumptions!B18 -> 0 | J20: =J11*Assumptions!B18 -> 0 | K20: =K11*Assumptions!B18 -> 0 | L20: =L11*Assumptions!B18 -> 0 | M20: =M11*Assumptions!B18 -> 0 | N20: =SUM(B20:M20) -> 0 | O20: =O11*Assumptions!C18 -> 0 | P20: =IF(O20<>0,(N20-O20)/ABS(O20),0) -> 0
A21: General & Administrative | B21: =B11*Assumptions!B19 -> 0 | C21: =C11*Assumptions!B19 -> 0 | D21: =D11*Assumptions!B19 -> 0 | E21: =E11*Assumptions!B19 -> 0 | F21: =F11*Assumptions!B19 -> 0 | G21: =G11*Assumptions!B19 -> 0 | H21: =H11*Assumptions!B19 -> 0 | I21: =I11*Assumptions!B19 -> 0 | J21: =J11*Assumptions!B19 -> 0 | K21: =K11*Assumptions!B19 -> 0 | L21: =L11*Assumptions!B19 -> 0 | M21: =M11*Assumptions!B19 -> 0 | N21: =SUM(B21:M21) -> 0 | O21: =O11*Assumptions!C19 -> 0 | P21: =IF(O21<>0,(N21-O21)/ABS(O21),0) -> 0
A22: Depreciation & Amortization | B22: =Assumptions!B20/12 -> 0 | C22: =Assumptions!B20/12 -> 0 | D22: =Assumptions!B20/12 -> 0 | E22: =Assumptions!B20/12 -> 0 | F22: =Assumptions!B20/12 -> 0 | G22: =Assumptions!B20/12 -> 0 | H22: =Assumptions!B20/12 -> 0 | I22: =Assumptions!B20/12 -> 0 | J22: =Assumptions!B20/12 -> 0 | K22: =Assumptions!B20/12 -> 0 | L22: =Assumptions!B20/12 -> 0 | M22: =Assumptions!B20/12 -> 0 | N22: =SUM(B22:M22) -> 0 | O22: =Assumptions!C20 -> 165000 | P22: =IF(O22<>0,(N22-O22)/ABS(O22),0) -> -1
A23: TOTAL OPEX | B23: =SUM(B19:B22) -> 0 | C23: =SUM(C19:C22) -> 0 | D23: =SUM(D19:D22) -> 0 | E23: =SUM(E19:E22) -> 0 | F23: =SUM(F19:F22) -> 0 | G23: =SUM(G19:G22) -> 0 | H23: =SUM(H19:H22) -> 0 | I23: =SUM(I19:I22) -> 0 | ... O23: =SUM(O19:O22) -> 165000 | P23: =IF(O23<>0,(N23-O23)/ABS(O23),0) -> -1
A25: EBITDA | B25: =B15-B23+B22 -> 0 | C25: =C15-C23+C22 -> 0 | D25: =D15-D23+D22 -> 0 | E25: =E15-E23+E22 -> 0 | F25: =F15-F23+F22 -> 0 | G25: =G15-G23+G22 -> 0 | H25: =H15-H23+H22 -> 0 | I25: =I15-I23+I22 -> 0 | ... O25: =O15-O23+O22 -> 0 | P25: =IF(O25<>0,(N25-O25)/ABS(O25),0) -> 0
A26: EBITDA Margin % | B26: =IF(B11<>0,B25/B11,0) -> 0 | C26: =IF(C11<>0,C25/C11,0) -> 0 | D26: =IF(D11<>0,D25/D11,0) -> 0 | E26: =IF(E11<>0,E25/E11,0) -> 0 | F26: =IF(F11<>0,F25/F11,0) -> 0 | G26: =IF(G11<>0,G25/G11,0) -> 0 | H26: =IF(H11<>0,H25/H11,0) -> 0 | I26: =IF(I11<>0,I25/I11,0) -> 0 | ... O26: =IF(O11<>0,O25/O11,0) -> 0
A28: Interest Expense | B28: =Assumptions!B21/12 -> 0 | C28: =Assumptions!B21/12 -> 0 | D28: =Assumptions!B21/12 -> 0 | E28: =Assumptions!B21/12 -> 0 | F28: =Assumptions!B21/12 -> 0 | G28: =Assumptions!B21/12 -> 0 | H28: =Assumptions!B21/12 -> 0 | I28: =Assumptions!B21/12 -> 0 | J28: =Assumptions!B21/12 -> 0 | K28: =Assumptions!B21/12 -> 0 | L28: =Assumptions!B21/12 -> 0 | M28: =Assumptions!B21/12 -> 0 | N28: =SUM(B28:M28) -> 0 | O28: =Assumptions!C21 -> 50000 | P28: =IF(O28<>0,(N28-O28)/ABS(O28),0) -> -1
A29: EBT (Earnings Before Tax) | B29: =B25-B22-B28 -> 0 | C29: =C25-C22-C28 -> 0 | D29: =D25-D22-D28 -> 0 | E29: =E25-E22-E28 -> 0 | F29: =F25-F22-F28 -> 0 | G29: =G25-G22-G28 -> 0 | H29: =H25-H22-H28 -> 0 | I29: =I25-I22-I28 -> 0 | ... O29: =O25-O22-O28 -> -215000 | P29: =IF(O29<>0,(N29-O29)/ABS(O29),0) -> 1
A30: Income Tax | B30: =MAX(B29*Assumptions!B22,0) -> 0 | C30: =MAX(C29*Assumptions!B22,0) -> 0 | D30: =MAX(D29*Assumptions!B22,0) -> 0 | E30: =MAX(E29*Assumptions!B22,0) -> 0 | F30: =MAX(F29*Assumptions!B22,0) -> 0 | G30: =MAX(G29*Assumptions!B22,0) -> 0 | H30: =MAX(H29*Assumptions!B22,0) -> 0 | I30: =MAX(I29*Assumptions!B22,0) -> 0 | J30: =MAX(J29*Assumptions!B22,0) -> 0 | K30: =MAX(K29*Assumptions!B22,0) -> 0 | L30: =MAX(L29*Assumptions!B22,0) -> 0 | M30: =MAX(M29*Assumptions!B22,0) -> 0 | N30: =SUM(B30:M30) -> 0 | O30: =MAX(O29*Assumptions!C22,0) -> 0 | P30: =IF(O30<>0,(N30-O30)/ABS(O30),0) -> 0
A31: NET INCOME | B31: =B29-B30 -> 0 | C31: =C29-C30 -> 0 | D31: =D29-D30 -> 0 | E31: =E29-E30 -> 0 | F31: =F29-F30 -> 0 | G31: =G29-G30 -> 0 | H31: =H29-H30 -> 0 | I31: =I29-I30 -> 0 | ... O31: =O29-O30 -> -215000 | P31: =IF(O31<>0,(N31-O31)/ABS(O31),0) -> 1
A32: Net Margin % | B32: =IF(B11<>0,B31/B11,0) -> 0 | C32: =IF(C11<>0,C31/C11,0) -> 0 | D32: =IF(D11<>0,D31/D11,0) -> 0 | E32: =IF(E11<>0,E31/E11,0) -> 0 | F32: =IF(F11<>0,F31/F11,0) -> 0 | G32: =IF(G11<>0,G31/G11,0) -> 0 | H32: =IF(H11<>0,H31/H11,0) -> 0 | I32: =IF(I11<>0,I31/I11,0) -> 0 | ... O32: =IF(O11<>0,O31/O11,0) -> 0

Sheet Variance_Tracker
A1: FY2026 Actuals vs Budget — Variance Tracker
A3: Update the 'Current Month' cell and paste your actuals in column C. Variance columns auto-calculate.
A4: Current Month (1-12):
A6: P&L Line | B6: YTD Budget ($) | C6: YTD Actual ($) | D6: YTD Variance ($) | E6: YTD Var % | F6: FY Budget ($) | G6: FY Forecast ($) | H6: FY Variance ($) | I6: FY Var %
A7: TOTAL REVENUE | B7: =IFERROR(SUMPRODUCT((COLUMN(Budget_PL!B11:M11)-1<=$B$4)*Budget_PL!B11:M11),0) -> 0 | D7: =IFERROR(C7-B7,0) -> 0 | E7: =IFERROR(IF(B7<>0,(C7-B7)/ABS(B7),0),0) -> 0 | F7: =IFERROR(Budget_PL!N11,0) -> 0 | H7: =IFERROR(G7-F7,0) -> 0 | I7: =IFERROR(IF(F7<>0,(G7-F7)/ABS(F7),0),0) -> 0
A8: GROSS PROFIT | B8: =IFERROR(SUMPRODUCT((COLUMN(Budget_PL!B15:M15)-1<=$B$4)*Budget_PL!B15:M15),0) -> 0 | D8: =IFERROR(C8-B8,0) -> 0 | E8: =IFERROR(IF(B8<>0,(C8-B8)/ABS(B8),0),0) -> 0 | F8: =IFERROR(Budget_PL!N15,0) -> 0 | H8: =IFERROR(G8-F8,0) -> 0 | I8: =IFERROR(IF(F8<>0,(G8-F8)/ABS(F8),0),0) -> 0
A9: Gross Margin % | B9: =IFERROR(SUMPRODUCT((COLUMN(Budget_PL!B16:M16)-1<=$B$4)*Budget_PL!B16:M16),0) -> 0 | D9: =IFERROR(C9-B9,0) -> 0 | E9: =IFERROR(IF(B9<>0,(C9-B9)/ABS(B9),0),0) -> 0 | F9: =IFERROR(Budget_PL!N16,0) -> 0 | H9: =IFERROR(G9-F9,0) -> 0 | I9: =IFERROR(IF(F9<>0,(G9-F9)/ABS(F9),0),0) -> 0
A10: R&D | B10: =IFERROR(SUMPRODUCT((COLUMN(Budget_PL!B19:M19)-1<=$B$4)*Budget_PL!B19:M19),0) -> 0 | D10: =IFERROR(C10-B10,0) -> 0 | E10: =IFERROR(IF(B10<>0,(C10-B10)/ABS(B10),0),0) -> 0 | F10: =IFERROR(Budget_PL!N19,0) -> 0 | H10: =IFERROR(G10-F10,0) -> 0 | I10: =IFERROR(IF(F10<>0,(G10-F10)/ABS(F10),0),0) -> 0
A11: Sales & Marketing | B11: =IFERROR(SUMPRODUCT((COLUMN(Budget_PL!B20:M20)-1<=$B$4)*Budget_PL!B20:M20),0) -> 0 | D11: =IFERROR(C11-B11,0) -> 0 | E11: =IFERROR(IF(B11<>0,(C11-B11)/ABS(B11),0),0) -> 0 | F11: =IFERROR(Budget_PL!N20,0) -> 0 | H11: =IFERROR(G11-F11,0) -> 0 | I11: =IFERROR(IF(F11<>0,(G11-F11)/ABS(F11),0),0) -> 0
A12: G&A | B12: =IFERROR(SUMPRODUCT((COLUMN(Budget_PL!B21:M21)-1<=$B$4)*Budget_PL!B21:M21),0) -> 0 | D12: =IFERROR(C12-B12,0) -> 0 | E12: =IFERROR(IF(B12<>0,(C12-B12)/ABS(B12),0),0) -> 0 | F12: =IFERROR(Budget_PL!N21,0) -> 0 | H12: =IFERROR(G12-F12,0) -> 0 | I12: =IFERROR(IF(F12<>0,(G12-F12)/ABS(F12),0),0) -> 0
A13: D&A | B13: =IFERROR(SUMPRODUCT((COLUMN(Budget_PL!B22:M22)-1<=$B$4)*Budget_PL!B22:M22),0) -> 0 | D13: =IFERROR(C13-B13,0) -> 0 | E13: =IFERROR(IF(B13<>0,(C13-B13)/ABS(B13),0),0) -> 0 | F13: =IFERROR(Budget_PL!N22,0) -> 0 | H13: =IFERROR(G13-F13,0) -> 0 | I13: =IFERROR(IF(F13<>0,(G13-F13)/ABS(F13),0),0) -> 0
A14: TOTAL OPEX | B14: =IFERROR(SUMPRODUCT((COLUMN(Budget_PL!B23:M23)-1<=$B$4)*Budget_PL!B23:M23),0) -> 0 | D14: =IFERROR(C14-B14,0) -> 0 | E14: =IFERROR(IF(B14<>0,(C14-B14)/ABS(B14),0),0) -> 0 | F14: =IFERROR(Budget_PL!N23,0) -> 0 | H14: =IFERROR(G14-F14,0) -> 0 | I14: =IFERROR(IF(F14<>0,(G14-F14)/ABS(F14),0),0) -> 0
A15: EBITDA | B15: =IFERROR(SUMPRODUCT((COLUMN(Budget_PL!B25:M25)-1<=$B$4)*Budget_PL!B25:M25),0) -> 0 | D15: =IFERROR(C15-B15,0) -> 0 | E15: =IFERROR(IF(B15<>0,(C15-B15)/ABS(B15),0),0) -> 0 | F15: =IFERROR(Budget_PL!N25,0) -> 0 | H15: =IFERROR(G15-F15,0) -> 0 | I15: =IFERROR(IF(F15<>0,(G15-F15)/ABS(F15),0),0) -> 0
A16: EBITDA Margin % | B16: =IFERROR(SUMPRODUCT((COLUMN(Budget_PL!B26:M26)-1<=$B$4)*Budget_PL!B26:M26),0) -> 0 | D16: =IFERROR(C16-B16,0) -> 0 | E16: =IFERROR(IF(B16<>0,(C16-B16)/ABS(B16),0),0) -> 0 | F16: =IFERROR(Budget_PL!N26,0) -> 0 | H16: =IFERROR(G16-F16,0) -> 0 | I16: =IFERROR(IF(F16<>0,(G16-F16)/ABS(F16),0),0) -> 0
A17: NET INCOME | B17: =IFERROR(SUMPRODUCT((COLUMN(Budget_PL!B31:M31)-1<=$B$4)*Budget_PL!B31:M31),0) -> 0 | D17: =IFERROR(C17-B17,0) -> 0 | E17: =IFERROR(IF(B17<>0,(C17-B17)/ABS(B17),0),0) -> 0 | F17: =IFERROR(Budget_PL!N31,0) -> 0 | H17: =IFERROR(G17-F17,0) -> 0 | I17: =IFERROR(IF(F17<>0,(G17-F17)/ABS(F17),0),0) -> 0
A18: Net Margin % | B18: =IFERROR(SUMPRODUCT((COLUMN(Budget_PL!B32:M32)-1<=$B$4)*Budget_PL!B32:M32),0) -> 0 | D18: =IFERROR(C18-B18,0) -> 0 | E18: =IFERROR(IF(B18<>0,(C18-B18)/ABS(B18),0),0) -> 0 | F18: =IFERROR(Budget_PL!N32,0) -> 0 | H18: =IFERROR(G18-F18,0) -> 0 | I18: =IFERROR(IF(F18<>0,(G18-F18)/ABS(F18),0),0) -> 0
A21: 💡 Tip: Positive variance = Favorable (Revenue above budget or Cost below budget)
