Workbook

Sheet Pricing_Assumptions
A1: FY2026 Pricing Initiatives — Assumptions & Inputs
A3: Enter current prices, proposed increases, and elasticity assumptions. All scenario tabs pull from here.
A5: A. CURRENT PRICING & VOLUME BASELINE (FY2025 Actuals)
A6: Product / SKU | B6: Avg Selling Price ($) | C6: Annual Units Sold | D6: Annual Revenue ($) | E6: COGS per Unit ($) | F6: Gross Margin per Unit ($) | G6: GM % | H6: Customer Segment | I6: Channel | J6: Notes
A7: Product A | B7: 450 | C7: 4000 | D7: =B7*C7 -> 1800000 | E7: 175 | F7: =B7-E7 -> 275 | G7: =IF(B7<>0,F7/B7,0) -> 0.61111111 | H7: Enterprise | I7: Direct
A8: Product B | B8: 320 | C8: 3938 | D8: =B8*C8 -> 1260160 | E8: 130 | F8: =B8-E8 -> 190 | G8: =IF(B8<>0,F8/B8,0) -> 0.59375 | H8: Mid-Market | I8: Partner
A9: Product C | B9: 180 | C9: 4000 | D9: =B9*C9 -> 720000 | E9: 65 | F9: =B9-E9 -> 115 | G9: =IF(B9<>0,F9/B9,0) -> 0.63888889 | H9: SMB | I9: Online
A10: Product D | B10: 95 | C10: 4737 | D10: =B10*C10 -> 450015 | E10: 42 | F10: =B10-E10 -> 53 | G10: =IF(B10<>0,F10/B10,0) -> 0.55789474 | H10: SMB | I10: Online
A11: Other Rev | B11: 125 | C11: 1800 | D11: =B11*C11 -> 225000 | E11: 50 | F11: =B11-E11 -> 75 | G11: =IF(B11<>0,F11/B11,0) -> 0.6 | H11: All Segments | I11: Various
A12: TOTAL BASELINE | D12: =SUM(D7:D11) -> 4455175
A14: B. PROPOSED PRICE CHANGES BY INITIATIVE
A15: Product / SKU | B15: Initiative Name | C15: Price Change Type | D15: Current Price ($) | E15: Proposed Price ($) | F15: % Change | G15: Price Elasticity (e) | H15: Volume Impact % | I15: New Volume | J15: New Revenue ($) | K15: Revenue Impact ($) | L15: Status
A16: Product A | B16: Enterprise Tier Increase | C16: List Price | D16: =B7 -> 450 | E16: 486 | F16: =IF(D16<>0,(E16-D16)/D16,0) -> 0.08 | G16: -0.4 | H16: =G16*F16 -> -0.032 | I16: =C7*(1+H16) -> 3872 | J16: =E16*I16 -> 1881792 | K16: =J16-D16*C7 -> 81792 | L16: Approved
A17: Product B | B17: Mid-Market Realignment | C17: List Price | D17: =B8 -> 320 | E17: 336 | F17: =IF(D17<>0,(E17-D17)/D17,0) -> 0.05 | G17: -0.6 | H17: =G17*F17 -> -0.03 | I17: =C8*(1+H17) -> 3819.86 | J17: =E17*I17 -> 1283473 | K17: =J17-D17*C8 -> 23312.96 | L17: In Review
A18: Product C | B18: SMB Bundle Reprice | C18: Bundle | D18: =B9 -> 180 | E18: 190.8 | F18: =IF(D18<>0,(E18-D18)/D18,0) -> 0.06 | G18: -0.8 | H18: =G18*F18 -> -0.048 | I18: =C9*(1+H18) -> 3808 | J18: =E18*I18 -> 726566.4 | K18: =J18-D18*C9 -> 6566.4 | L18: Approved
A19: Product D | B19: Entry SKU Optimization | C19: Promotional | D19: =B10 -> 95 | E19: 97.85 | F19: =IF(D19<>0,(E19-D19)/D19,0) -> 0.03 | G19: -1 | H19: =G19*F19 -> -0.03 | I19: =C10*(1+H19) -> 4594.89 | J19: =E19*I19 -> 449609.99 | K19: =J19-D19*C10 -> -405.0135 | L19: Planned
A20: Other Rev | B20: Services Rate Card Update | C20: Services | D20: =B11 -> 125 | E20: 137.5 | F20: =IF(D20<>0,(E20-D20)/D20,0) -> 0.1 | G20: -0.2 | H20: =G20*F20 -> -0.02 | I20: =C11*(1+H20) -> 1764 | J20: =E20*I20 -> 242550 | K20: =J20-D20*C11 -> 17550 | L20: In Review
A21: TOTAL IMPACT | J21: =SUM(J16:J20) -> 4583991.3 | K21: =SUM(K16:K20) -> 128816.35
A23: C. PRICE ELASTICITY REFERENCE GUIDE
A24: Elasticity Range | B24: Classification | C24: Example / Context
A25: 0.0 to -0.2 | B25: Very Inelastic | C25: Enterprise SaaS — sticky contracts, high switching cost
A26: -0.2 to -0.5 | B26: Inelastic | C26: Mid-market software — some alternatives but high switching
A27: -0.5 to -1.0 | B27: Unit Elastic | C27: SMB/online tools — moderate price sensitivity
A28: -1.0 to -2.0 | B28: Elastic | C28: Commoditized products — high substitution risk
A29: < -2.0 | B29: Highly Elastic | C29: Undifferentiated, price-driven markets

Sheet PVM_Bridge
A1: Price-Volume-Mix Bridge — Revenue Variance Analysis
A3: Decomposes total revenue variance into Price, Volume, and Mix effects. Update yellow cells with current period actuals.
A5: Product | B5: Prior Price ($) | C5: Current Price ($) | D5: Prior Volume | E5: Current Volume | F5: Prior Revenue ($) | G5: Current Revenue ($) | H5: Price Effect ($) | I5: Volume Effect ($) | J5: Mix Effect ($) | K5: Total Variance ($)
A6: Product A | B6: =Pricing_Assumptions!B7 -> 450 | C6: =Pricing_Assumptions!E16 -> 486 | D6: =Pricing_Assumptions!C7 -> 4000 | E6: =Pricing_Assumptions!I16 -> 3872 | F6: =B6*D6 -> 1800000 | G6: =C6*E6 -> 1881792 | H6: =(C6-B6)*D6 -> 144000 | I6: =B6*(E6-D6) -> -57600 | J6: =(G6-F6)-H6-I6 -> -4608 | K6: =G6-F6 -> 81792
A7: Product B | B7: =Pricing_Assumptions!B8 -> 320 | C7: =Pricing_Assumptions!E17 -> 336 | D7: =Pricing_Assumptions!C8 -> 3938 | E7: =Pricing_Assumptions!I17 -> 3819.86 | F7: =B7*D7 -> 1260160 | G7: =C7*E7 -> 1283473 | H7: =(C7-B7)*D7 -> 63008 | I7: =B7*(E7-D7) -> -37804.8 | J7: =(G7-F7)-H7-I7 -> -1890.24 | K7: =G7-F7 -> 23312.96
A8: Product C | B8: =Pricing_Assumptions!B9 -> 180 | C8: =Pricing_Assumptions!E18 -> 190.8 | D8: =Pricing_Assumptions!C9 -> 4000 | E8: =Pricing_Assumptions!I18 -> 3808 | F8: =B8*D8 -> 720000 | G8: =C8*E8 -> 726566.4 | H8: =(C8-B8)*D8 -> 43200 | I8: =B8*(E8-D8) -> -34560 | J8: =(G8-F8)-H8-I8 -> -2073.6 | K8: =G8-F8 -> 6566.4
A9: Product D | B9: =Pricing_Assumptions!B10 -> 95 | C9: =Pricing_Assumptions!E19 -> 97.85 | D9: =Pricing_Assumptions!C10 -> 4737 | E9: =Pricing_Assumptions!I19 -> 4594.89 | F9: =B9*D9 -> 450015 | G9: =C9*E9 -> 449609.99 | H9: =(C9-B9)*D9 -> 13500.45 | I9: =B9*(E9-D9) -> -13500.45 | J9: =(G9-F9)-H9-I9 -> -405.0135 | K9: =G9-F9 -> -405.0135
A10: Other Rev | B10: =Pricing_Assumptions!B11 -> 125 | C10: =Pricing_Assumptions!E20 -> 137.5 | D10: =Pricing_Assumptions!C11 -> 1800 | E10: =Pricing_Assumptions!I20 -> 1764 | F10: =B10*D10 -> 225000 | G10: =C10*E10 -> 242550 | H10: =(C10-B10)*D10 -> 22500 | I10: =B10*(E10-D10) -> -4500 | J10: =(G10-F10)-H10-I10 -> -450 | K10: =G10-F10 -> 17550
A11: TOTAL | F11: =SUM(F6:F10) -> 4455175 | G11: =SUM(G6:G10) -> 4583991.3 | H11: =SUM(H6:H10) -> 286208.45 | I11: =SUM(I6:I10) -> -147965.25 | J11: =SUM(J6:J10) -> -9426.8535 | K11: =SUM(K6:K10) -> 128816.35
A13: BRIDGE SUMMARY
A14: Prior Period Revenue | B14: =F11 -> 4455175
A15: + Price Effect | B15: =H11 -> 286208.45
A16: + Volume Effect | B16: =I11 -> -147965.25
A17: + Mix Effect | B17: =J11 -> -9426.8535
A18: =Current Period Revenue -> #NAME? | B18: =G11 -> 4583991.3
A19: Total Variance $ | B19: =K11 -> 128816.35
A20: Total Variance % | B20: =IF(F11<>0,K11/F11,0) -> 0.028913869

Sheet Initiative_Tracker
A1: Pricing Initiative Tracker — Implementation Roadmap FY2026
A3: Initiative Name | B3: Product | C3: Type | D3: Owner | E3: Target Eff. Date | F3: Status | G3: Revenue Impact ($) | H3: Vol. Impact % | I3: Risk Level | J3: Approver | K3: Approval Date | L3: Notes | M3: Completed?
A4: Enterprise Tier Increase | B4: Product A | C4: List Price | D4: Pricing Team | E4: 46079 | F4: Approved | G4: =Pricing_Assumptions!K16 -> 81792 | H4: =Pricing_Assumptions!H16 -> -0.032 | I4: Low | J4: CFO | M4: N
A5: Mid-Market Realignment | B5: Product B | C5: List Price | D5: Pricing Team | E5: 46107 | F5: In Review | G5: =Pricing_Assumptions!K17 -> 23312.96 | H5: =Pricing_Assumptions!H17 -> -0.03 | I5: Medium | J5: VP Sales | M5: N
A6: SMB Bundle Reprice | B6: Product C | C6: Bundle | D6: Product Mgmt | E6: 46138 | F6: Approved | G6: =Pricing_Assumptions!K18 -> 6566.4 | H6: =Pricing_Assumptions!H18 -> -0.048 | I6: Medium | J6: CFO | M6: N
A7: Entry SKU Optimization | B7: Product D | C7: Promotional | D7: Marketing | E7: Q2-26 | F7: Planned | G7: =Pricing_Assumptions!K19 -> -405.0135 | H7: =Pricing_Assumptions!H19 -> -0.03 | I7: Low | J7: VP Marketing | M7: N
A8: Services Rate Card Update | B8: Other Rev | C8: Services | D8: CS Team | E8: 46048 | F8: In Review | G8: =Pricing_Assumptions!K20 -> 17550 | H8: =Pricing_Assumptions!H20 -> -0.02 | I8: Low | J8: COO | M8: N
A10: PORTFOLIO SUMMARY
A11: Total Initiatives | B11: =COUNTA(A4:A8) -> 5
A12: Approved | B12: =COUNTIF(F4:F8,"Approved") -> 2
A13: In Review | B13: =COUNTIF(F4:F8,"In Review") -> 2
A14: Planned | B14: =COUNTIF(F4:F8,"Planned") -> 1
A15: Total Revenue Impact (Base) | B15: =SUM(G4:G8) -> 128816.35
A16: Approved Initiatives Impact | B16: =SUMIF(F4:F8,"Approved",G4:G8) -> 88358.4

Sheet Scenario_Analysis
A1: Pricing Scenario Analysis — P&L Impact
A3: Three scenarios modeled: Conservative (partial rollout), Base (full rollout), Aggressive (above-plan stretch). Yellow cells = inputs.
A5: SCENARIO INPUTS — PRICE INCREASE % BY PRODUCT
A6: Product | B6: Current Price ($) | C6: Current Revenue ($) | D6: Conservative % | E6: Conservative Rev ($) | F6: Base Case % | G6: Base Case Rev ($) | H6: Aggressive % | I6: Aggressive Rev ($) | J6: Cons. Impact ($) | K6: Base Impact ($) | L6: Agg. Impact ($) | M6: Best Case | N6: Worst Case
A7: Product A | B7: =Pricing_Assumptions!B7 -> 450 | C7: =Pricing_Assumptions!D7 -> 1800000 | D7: 0.04 | E7: =C7*(1+D7)*(1+Pricing_Assumptions!G16*D7) -> 1842048 | F7: 0.08 | G7: =C7*(1+F7)*(1+Pricing_Assumptions!G16*F7) -> 1881792 | H7: 0.12 | I7: =C7*(1+H7)*(1+Pricing_Assumptions!G16*H7) -> 1919232 | J7: =E7-C7 -> 42048 | K7: =G7-C7 -> 81792 | L7: =I7-C7 -> 119232 | M7: =MAX(J7,K7,L7) -> 119232 | N7: =MIN(J7,K7,L7) -> 42048
A8: Product B | B8: =Pricing_Assumptions!B8 -> 320 | C8: =Pricing_Assumptions!D8 -> 1260160 | D8: 0.03 | E8: =C8*(1+D8)*(1+Pricing_Assumptions!G17*D8) -> 1274601.4 | F8: 0.05 | G8: =C8*(1+F8)*(1+Pricing_Assumptions!G17*F8) -> 1283473 | H8: 0.08 | I8: =C8*(1+H8)*(1+Pricing_Assumptions!G17*H8) -> 1295646.1 | J8: =E8-C8 -> 14441.434 | K8: =G8-C8 -> 23312.96 | L8: =I8-C8 -> 35486.106 | M8: =MAX(J8,K8,L8) -> 35486.106 | N8: =MIN(J8,K8,L8) -> 14441.434
A9: Product C | B9: =Pricing_Assumptions!B9 -> 180 | C9: =Pricing_Assumptions!D9 -> 720000 | D9: 0.03 | E9: =C9*(1+D9)*(1+Pricing_Assumptions!G18*D9) -> 723801.6 | F9: 0.06 | G9: =C9*(1+F9)*(1+Pricing_Assumptions!G18*F9) -> 726566.4 | H9: 0.1 | I9: =C9*(1+H9)*(1+Pricing_Assumptions!G18*H9) -> 728640 | J9: =E9-C9 -> 3801.6 | K9: =G9-C9 -> 6566.4 | L9: =I9-C9 -> 8640 | M9: =MAX(J9,K9,L9) -> 8640 | N9: =MIN(J9,K9,L9) -> 3801.6
A10: Product D | B10: =Pricing_Assumptions!B10 -> 95 | C10: =Pricing_Assumptions!D10 -> 450015 | D10: 0.02 | E10: =C10*(1+D10)*(1+Pricing_Assumptions!G19*D10) -> 449834.99 | F10: 0.03 | G10: =C10*(1+F10)*(1+Pricing_Assumptions!G19*F10) -> 449609.99 | H10: 0.05 | I10: =C10*(1+H10)*(1+Pricing_Assumptions!G19*H10) -> 448889.96 | J10: =E10-C10 -> -180.006 | K10: =G10-C10 -> -405.0135 | L10: =I10-C10 -> -1125.0375 | M10: =MAX(J10,K10,L10) -> -180.006 | N10: =MIN(J10,K10,L10) -> -1125.0375
A11: Other Rev | B11: =Pricing_Assumptions!B11 -> 125 | C11: =Pricing_Assumptions!D11 -> 225000 | D11: 0.05 | E11: =C11*(1+D11)*(1+Pricing_Assumptions!G20*D11) -> 233887.5 | F11: 0.1 | G11: =C11*(1+F11)*(1+Pricing_Assumptions!G20*F11) -> 242550 | H11: 0.15 | I11: =C11*(1+H11)*(1+Pricing_Assumptions!G20*H11) -> 250987.5 | J11: =E11-C11 -> 8887.5 | K11: =G11-C11 -> 17550 | L11: =I11-C11 -> 25987.5 | M11: =MAX(J11,K11,L11) -> 25987.5 | N11: =MIN(J11,K11,L11) -> 8887.5
A12: TOTAL | C12: =SUM(C7:C11) -> 4455175 | D12: =SUM(D7:D11) -> 0.17 | E12: =SUM(E7:E11) -> 4524173.5 | F12: =SUM(F7:F11) -> 0.32 | G12: =SUM(G7:G11) -> 4583991.3 | H12: =SUM(H7:H11) -> 0.5 | I12: =SUM(I7:I11) -> 4643395.6 | J12: =SUM(J7:J11) -> 68998.528 | ... N12: =SUM(N7:N11) -> 68053.496
A13: MARGIN ASSUMPTIONS (apply to all scenarios)
A14: Gross Margin % | C14: OPEX % | E14: Tax rate %
A15: Metric | B15: Baseline | C15: Conservative | D15: Base Case | E15: Aggressive | F15: Cons. vs BL | G15: Base vs BL | H15: Agg. vs BL
A16: Total Revenue | B16: =C12 -> 4455175 | C16: =E12 -> 4524173.5 | D16: =G12 -> 4583991.3 | E16: =I12 -> 4643395.6 | F16: =C16-B16 -> 68998.528 | G16: =D16-B16 -> 128816.35 | H16: =E16-B16 -> 188220.57
A17: Gross Profit | B17: =B16*$B$14 -> 0 | C17: =C16*$B$14 -> 0 | D17: =D16*$B$14 -> 0 | E17: =E16*$B$14 -> 0 | F17: =C17-B17 -> 0 | G17: =D17-B17 -> 0 | H17: =E17-B17 -> 0
A18: Gross Margin % | B18: =IF(B16<>0,B17/B16,0) -> 0 | C18: =IF(C16<>0,C17/C16,0) -> 0 | D18: =IF(D16<>0,D17/D16,0) -> 0 | E18: =IF(E16<>0,E17/E16,0) -> 0 | F18: =C18-B18 -> 0 | G18: =D18-B18 -> 0 | H18: =E18-B18 -> 0
A19: Total OPEX | B19: =B16*$D$14 -> 0 | C19: =C16*$D$14 -> 0 | D19: =D16*$D$14 -> 0 | E19: =E16*$D$14 -> 0 | F19: =C19-B19 -> 0 | G19: =D19-B19 -> 0 | H19: =E19-B19 -> 0
A20: EBITDA | B20: =B17-B19 -> 0 | C20: =C17-C19 -> 0 | D20: =D17-D19 -> 0 | E20: =E17-E19 -> 0 | F20: =C20-B20 -> 0 | G20: =D20-B20 -> 0 | H20: =E20-B20 -> 0
A21: EBITDA Margin % | B21: =IF(B16<>0,B20/B16,0) -> 0 | C21: =IF(C16<>0,C20/C16,0) -> 0 | D21: =IF(D16<>0,D20/D16,0) -> 0 | E21: =IF(E16<>0,E20/E16,0) -> 0 | F21: =C21-B21 -> 0 | G21: =D21-B21 -> 0 | H21: =E21-B21 -> 0
